[
    {
        "_id":"a-05",
        "_parentId":"co-05",
        "_type":"article",
        "title":"Article first title"
    },
    {
        "_id":"a-10",
        "_parentId":"co-05",
        "_type":"article",
        "title":"Article second title"
    },
    {
        "_id":"a-15",
        "_parentId":"co-15",
        "_type":"article",
        "title":"Article third title"
    },
    {
        "_id":"a-20",
        "_parentId":"co-20",
        "_type":"article",
        "title":"Article fourth title"
    }
]